<?xml version="1.0" encoding="UTF-8" standalone="no"?>
<annotation>
    <folder>NA</folder>
    <filename>22_jpg.rf.e03281d6ce640446605c9a53512103dd.jpg</filename>
    <source>
        <database>Unknown</database>
    </source>
    <size>
        <width>450</width>
        <height>450</height>
        <depth>3</depth>
    </size>
    <segmented>0</segmented>
    <object>
        <name>fire weapon</name>
        <pose>Unspecified</pose>
        <truncated>0</truncated>
        <difficult>0</difficult>
        <occluded>0</occluded>
        <bndbox>
            <xmin>341.0</xmin>
            <ymin>156.0</ymin>
            <xmax>400.0</xmax>
            <ymax>287.0</ymax>
        </bndbox>
    </object>
    <object>
        <name>fire weapon</name>
        <pose>Unspecified</pose>
        <truncated>0</truncated>
        <difficult>0</difficult>
        <occluded>0</occluded>
        <bndbox>
            <xmin>60.0</xmin>
            <ymin>162.0</ymin>
            <xmax>165.0</xmax>
            <ymax>299.0</ymax>
        </bndbox>
    </object>
</annotation>
