<?xml version="1.0" encoding="UTF-8" standalone="no"?>
<annotation>
    <folder>NA</folder>
    <filename>armas__1573__jpg.rf.6f5997f6bbc90c6b57fdfac70794eb2e.jpg</filename>
    <source>
        <database>Unknown</database>
    </source>
    <size>
        <width>450</width>
        <height>450</height>
        <depth>3</depth>
    </size>
    <segmented>0</segmented>
    <object>
        <name>fire weapon</name>
        <pose>Unspecified</pose>
        <truncated>0</truncated>
        <difficult>0</difficult>
        <occluded>0</occluded>
        <bndbox>
            <xmin>168.0</xmin>
            <ymin>3.0</ymin>
            <xmax>426.0</xmax>
            <ymax>355.0</ymax>
        </bndbox>
    </object>
    <object>
        <name>fire weapon</name>
        <pose>Unspecified</pose>
        <truncated>0</truncated>
        <difficult>0</difficult>
        <occluded>0</occluded>
        <bndbox>
            <xmin>81.0</xmin>
            <ymin>5.0</ymin>
            <xmax>235.0</xmax>
            <ymax>247.0</ymax>
        </bndbox>
    </object>
</annotation>
