<?xml version="1.0" encoding="UTF-8" standalone="no"?>
<annotation>
    <folder>NA</folder>
    <filename>armas__1564__jpg.rf.c094e874beb8fa23186f5a7974926e76.jpg</filename>
    <source>
        <database>Unknown</database>
    </source>
    <size>
        <width>450</width>
        <height>450</height>
        <depth>3</depth>
    </size>
    <segmented>0</segmented>
    <object>
        <name>fire weapon</name>
        <pose>Unspecified</pose>
        <truncated>0</truncated>
        <difficult>0</difficult>
        <occluded>0</occluded>
        <bndbox>
            <xmin>16.0</xmin>
            <ymin>85.0</ymin>
            <xmax>440.0</xmax>
            <ymax>329.0</ymax>
        </bndbox>
    </object>
</annotation>
