<?xml version="1.0" encoding="UTF-8" standalone="no"?>
<annotation>
    <folder>NA</folder>
    <filename>armas__2640__jpg.rf.15c11bae5c939062ff8c71017bd0776d.jpg</filename>
    <source>
        <database>Unknown</database>
    </source>
    <size>
        <width>450</width>
        <height>450</height>
        <depth>3</depth>
    </size>
    <segmented>0</segmented>
    <object>
        <name>fire weapon</name>
        <pose>Unspecified</pose>
        <truncated>0</truncated>
        <difficult>0</difficult>
        <occluded>0</occluded>
        <bndbox>
            <xmin>4.0</xmin>
            <ymin>16.0</ymin>
            <xmax>434.0</xmax>
            <ymax>444.0</ymax>
        </bndbox>
    </object>
</annotation>
