<?xml version="1.0" encoding="UTF-8" standalone="no"?>
<annotation>
    <folder>NA</folder>
    <filename>aug1--198-_jpg.rf.ad070b8fd30e42ebb9784c05efcf8c76.jpg</filename>
    <source>
        <database>Unknown</database>
    </source>
    <size>
        <width>450</width>
        <height>450</height>
        <depth>3</depth>
    </size>
    <segmented>0</segmented>
    <object>
        <name>fire weapon</name>
        <pose>Unspecified</pose>
        <truncated>0</truncated>
        <difficult>0</difficult>
        <occluded>0</occluded>
        <bndbox>
            <xmin>317.0</xmin>
            <ymin>258.0</ymin>
            <xmax>360.0</xmax>
            <ymax>285.0</ymax>
        </bndbox>
    </object>
</annotation>
