<?xml version="1.0" encoding="UTF-8" standalone="no"?>
<annotation>
    <folder>NA</folder>
    <filename>augarmas--2026-_jpg.rf.99b9e75a77dcd3c9158921b6f0d24e0d.jpg</filename>
    <source>
        <database>Unknown</database>
    </source>
    <size>
        <width>450</width>
        <height>450</height>
        <depth>3</depth>
    </size>
    <segmented>0</segmented>
    <object>
        <name>fire weapon</name>
        <pose>Unspecified</pose>
        <truncated>0</truncated>
        <difficult>0</difficult>
        <occluded>0</occluded>
        <bndbox>
            <xmin>90.0</xmin>
            <ymin>191.0</ymin>
            <xmax>114.0</xmax>
            <ymax>223.0</ymax>
        </bndbox>
    </object>
</annotation>
