<?xml version="1.0" encoding="UTF-8" standalone="no"?>
<annotation>
    <folder>NA</folder>
    <filename>augarmas--879-_jpg.rf.6a50e8ee98e60f5ee5ffa9c222e4b9e8.jpg</filename>
    <source>
        <database>Unknown</database>
    </source>
    <size>
        <width>450</width>
        <height>450</height>
        <depth>3</depth>
    </size>
    <segmented>0</segmented>
    <object>
        <name>fire weapon</name>
        <pose>Unspecified</pose>
        <truncated>0</truncated>
        <difficult>0</difficult>
        <occluded>0</occluded>
        <bndbox>
            <xmin>284.0</xmin>
            <ymin>186.0</ymin>
            <xmax>316.0</xmax>
            <ymax>219.0</ymax>
        </bndbox>
    </object>
</annotation>
