<?xml version="1.0" encoding="UTF-8" standalone="no"?>
<annotation>
    <folder>NA</folder>
    <filename>augbeautiful-army-girl-gun-isolated-over-black-background-adult-armed-armor-battle-game-hand-special-female-trigger-warrior-157054723_jpg.rf.f10f9cd90720610e36a4d9daab9e8d7c.jpg</filename>
    <source>
        <database>Unknown</database>
    </source>
    <size>
        <width>450</width>
        <height>450</height>
        <depth>3</depth>
    </size>
    <segmented>0</segmented>
    <object>
        <name>fire weapon</name>
        <pose>Unspecified</pose>
        <truncated>0</truncated>
        <difficult>0</difficult>
        <occluded>0</occluded>
        <bndbox>
            <xmin>283.0</xmin>
            <ymin>168.0</ymin>
            <xmax>322.0</xmax>
            <ymax>216.0</ymax>
        </bndbox>
    </object>
</annotation>
