<?xml version="1.0" encoding="UTF-8" standalone="no"?>
<annotation>
    <folder>NA</folder>
    <filename>DW9MAJ2NSLC2_jpg.rf.b8c3f8971512be27f634c39f25ebe7d5.jpg</filename>
    <source>
        <database>Unknown</database>
    </source>
    <size>
        <width>450</width>
        <height>450</height>
        <depth>3</depth>
    </size>
    <segmented>0</segmented>
    <object>
        <name>fire weapon</name>
        <pose>Unspecified</pose>
        <truncated>0</truncated>
        <difficult>0</difficult>
        <occluded>0</occluded>
        <bndbox>
            <xmin>1.0</xmin>
            <ymin>160.0</ymin>
            <xmax>184.0</xmax>
            <ymax>276.0</ymax>
        </bndbox>
    </object>
</annotation>
