<?xml version="1.0" encoding="UTF-8" standalone="no"?>
<annotation>
    <folder>NA</folder>
    <filename>F3PFS9IRE65V_jpg.rf.b926b1017ea6b83d782b04cfb20ed9f6.jpg</filename>
    <source>
        <database>Unknown</database>
    </source>
    <size>
        <width>450</width>
        <height>450</height>
        <depth>3</depth>
    </size>
    <segmented>0</segmented>
    <object>
        <name>fire weapon</name>
        <pose>Unspecified</pose>
        <truncated>0</truncated>
        <difficult>0</difficult>
        <occluded>0</occluded>
        <bndbox>
            <xmin>86.0</xmin>
            <ymin>118.0</ymin>
            <xmax>435.0</xmax>
            <ymax>382.0</ymax>
        </bndbox>
    </object>
</annotation>
