<?xml version="1.0" encoding="UTF-8" standalone="no"?>
<annotation>
    <folder>NA</folder>
    <filename>HYE7XI553B23_jpg.rf.f6670dc9d985bcd57eff4ab0df511cf6.jpg</filename>
    <source>
        <database>Unknown</database>
    </source>
    <size>
        <width>450</width>
        <height>450</height>
        <depth>3</depth>
    </size>
    <segmented>0</segmented>
    <object>
        <name>fire weapon</name>
        <pose>Unspecified</pose>
        <truncated>0</truncated>
        <difficult>0</difficult>
        <occluded>0</occluded>
        <bndbox>
            <xmin>158.0</xmin>
            <ymin>167.0</ymin>
            <xmax>265.0</xmax>
            <ymax>273.0</ymax>
        </bndbox>
    </object>
    <object>
        <name>fire weapon</name>
        <pose>Unspecified</pose>
        <truncated>0</truncated>
        <difficult>0</difficult>
        <occluded>0</occluded>
        <bndbox>
            <xmin>1.0</xmin>
            <ymin>181.0</ymin>
            <xmax>69.0</xmax>
            <ymax>447.0</ymax>
        </bndbox>
    </object>
</annotation>
