<?xml version="1.0" encoding="UTF-8" standalone="no"?>
<annotation>
    <folder>NA</folder>
    <filename>knife_1008_jpg.rf.83abb122070037c897975b145b100e74.jpg</filename>
    <source>
        <database>Unknown</database>
    </source>
    <size>
        <width>450</width>
        <height>450</height>
        <depth>3</depth>
    </size>
    <segmented>0</segmented>
    <object>
        <name>knife</name>
        <pose>Unspecified</pose>
        <truncated>0</truncated>
        <difficult>0</difficult>
        <occluded>0</occluded>
        <bndbox>
            <xmin>79.0</xmin>
            <ymin>71.0</ymin>
            <xmax>113.0</xmax>
            <ymax>200.0</ymax>
        </bndbox>
    </object>
</annotation>
