<?xml version="1.0" encoding="UTF-8" standalone="no"?>
<annotation>
    <folder>NA</folder>
    <filename>KravMagaTraining344_jpg.rf.7fa6da1df45622a755e25a3b41c60cd8.jpg</filename>
    <source>
        <database>Unknown</database>
    </source>
    <size>
        <width>450</width>
        <height>450</height>
        <depth>3</depth>
    </size>
    <segmented>0</segmented>
    <object>
        <name>knife</name>
        <pose>Unspecified</pose>
        <truncated>0</truncated>
        <difficult>0</difficult>
        <occluded>0</occluded>
        <bndbox>
            <xmin>214.0</xmin>
            <ymin>199.0</ymin>
            <xmax>230.0</xmax>
            <ymax>289.0</ymax>
        </bndbox>
    </object>
</annotation>
