<?xml version="1.0" encoding="UTF-8" standalone="no"?>
<annotation>
    <folder>NA</folder>
    <filename>KravMagaTraining20846_jpg.rf.50c9278e6f9508b139b77276684e0ae1.jpg</filename>
    <source>
        <database>Unknown</database>
    </source>
    <size>
        <width>450</width>
        <height>450</height>
        <depth>3</depth>
    </size>
    <segmented>0</segmented>
    <object>
        <name>knife</name>
        <pose>Unspecified</pose>
        <truncated>0</truncated>
        <difficult>0</difficult>
        <occluded>0</occluded>
        <bndbox>
            <xmin>251.0</xmin>
            <ymin>324.0</ymin>
            <xmax>307.0</xmax>
            <ymax>367.0</ymax>
        </bndbox>
    </object>
</annotation>
