<?xml version="1.0" encoding="UTF-8" standalone="no"?>
<annotation>
    <folder>NA</folder>
    <filename>National_Firearms_Museum__Vietnam_era_rifles_jpg.rf.3babf4a3ddc9c444b24ece22fa225e2a.jpg</filename>
    <source>
        <database>Unknown</database>
    </source>
    <size>
        <width>450</width>
        <height>450</height>
        <depth>3</depth>
    </size>
    <segmented>0</segmented>
    <object>
        <name>fire weapon</name>
        <pose>Unspecified</pose>
        <truncated>0</truncated>
        <difficult>0</difficult>
        <occluded>0</occluded>
        <bndbox>
            <xmin>12.0</xmin>
            <ymin>249.0</ymin>
            <xmax>429.0</xmax>
            <ymax>307.0</ymax>
        </bndbox>
    </object>
    <object>
        <name>fire weapon</name>
        <pose>Unspecified</pose>
        <truncated>0</truncated>
        <difficult>0</difficult>
        <occluded>0</occluded>
        <bndbox>
            <xmin>14.0</xmin>
            <ymin>298.0</ymin>
            <xmax>427.0</xmax>
            <ymax>351.0</ymax>
        </bndbox>
    </object>
    <object>
        <name>fire weapon</name>
        <pose>Unspecified</pose>
        <truncated>0</truncated>
        <difficult>0</difficult>
        <occluded>0</occluded>
        <bndbox>
            <xmin>6.0</xmin>
            <ymin>345.0</ymin>
            <xmax>424.0</xmax>
            <ymax>405.0</ymax>
        </bndbox>
    </object>
    <object>
        <name>fire weapon</name>
        <pose>Unspecified</pose>
        <truncated>0</truncated>
        <difficult>0</difficult>
        <occluded>0</occluded>
        <bndbox>
            <xmin>10.0</xmin>
            <ymin>389.0</ymin>
            <xmax>420.0</xmax>
            <ymax>450.0</ymax>
        </bndbox>
    </object>
    <object>
        <name>fire weapon</name>
        <pose>Unspecified</pose>
        <truncated>0</truncated>
        <difficult>0</difficult>
        <occluded>0</occluded>
        <bndbox>
            <xmin>1.0</xmin>
            <ymin>44.0</ymin>
            <xmax>391.0</xmax>
            <ymax>94.0</ymax>
        </bndbox>
    </object>
    <object>
        <name>fire weapon</name>
        <pose>Unspecified</pose>
        <truncated>0</truncated>
        <difficult>0</difficult>
        <occluded>0</occluded>
        <bndbox>
            <xmin>30.0</xmin>
            <ymin>88.0</ymin>
            <xmax>410.0</xmax>
            <ymax>133.0</ymax>
        </bndbox>
    </object>
    <object>
        <name>fire weapon</name>
        <pose>Unspecified</pose>
        <truncated>0</truncated>
        <difficult>0</difficult>
        <occluded>0</occluded>
        <bndbox>
            <xmin>21.0</xmin>
            <ymin>143.0</ymin>
            <xmax>409.0</xmax>
            <ymax>194.0</ymax>
        </bndbox>
    </object>
    <object>
        <name>fire weapon</name>
        <pose>Unspecified</pose>
        <truncated>0</truncated>
        <difficult>0</difficult>
        <occluded>0</occluded>
        <bndbox>
            <xmin>18.0</xmin>
            <ymin>185.0</ymin>
            <xmax>404.0</xmax>
            <ymax>245.0</ymax>
        </bndbox>
    </object>
    <object>
        <name>fire weapon</name>
        <pose>Unspecified</pose>
        <truncated>0</truncated>
        <difficult>0</difficult>
        <occluded>0</occluded>
        <bndbox>
            <xmin>10.0</xmin>
            <ymin>4.0</ymin>
            <xmax>431.0</xmax>
            <ymax>44.0</ymax>
        </bndbox>
    </object>
</annotation>
